agent_interrogator/__init__.py
agent_interrogator/config.py
agent_interrogator/interrogator.py
agent_interrogator/llm.py
agent_interrogator/models.py
agent_interrogator/output.py
agent_interrogator/prompt_templates.py
agent_interrogator-0.1.1.dist-info/licenses/LICENSE
agent_interrogator-0.1.1.dist-info/METADATA
agent_interrogator-0.1.1.dist-info/WHEEL
agent_interrogator-0.1.1.dist-info/top_level.txt
agent_interrogator-0.1.1.dist-info/RECORD
